LICENSE.txt
MANIFEST.in
README.md
README.rst
setup.cfg
setup.py
django_dps.egg-info/PKG-INFO
django_dps.egg-info/SOURCES.txt
django_dps.egg-info/dependency_links.txt
django_dps.egg-info/requires.txt
django_dps.egg-info/top_level.txt
dps/__init__.py
dps/_version.py
dps/admin.py
dps/models.py
dps/transactions.py
dps/urls.py
dps/views.py
dps/migrations/0001_initial.py
dps/migrations/__init__.py
dps/south_migrations/0001_initial.py
dps/south_migrations/__init__.py
tests/__init__.py
tests/dps_settings.py
tests/models.py
tests/test_settings.py
tests/tests.py
tests/urls.py