Metadata-Version: 1.1
Name: django-dps
Version: 0.8
Summary: Django integrations for the DPS payment gateway
Home-page: https://github.com/gregplaysguitar/django-dps/
Author: Greg Brown
Author-email: greg@gregbrown.co.nz
License: BSD License
Platform: UNKNOWN
Classifier: Environment :: Web Environment
Classifier: Intended Audience :: Developers
Classifier: Operating System :: OS Independent
Classifier: Programming Language :: Python
Classifier: Programming Language :: Python :: 2
Classifier: Programming Language :: Python :: 2.7
Classifier: Framework :: Django
Classifier: License :: OSI Approved :: BSD License
